thulium/__init__.py
thulium/py.typed
thulium/version.py
thulium/api/__init__.py
thulium/api/recognition.py
thulium/api/recognize.py
thulium/api/types.py
thulium/cli/__init__.py
thulium/cli/main.py
thulium/cli/commands/__init__.py
thulium/cli/commands/analyze_errors_cmd.py
thulium/cli/commands/benchmark_cmd.py
thulium/cli/commands/pipelines_cmd.py
thulium/cli/commands/profiles_cmd.py
thulium/cli/commands/train_cmd.py
thulium/config/__init__.py
thulium/data/__init__.py
thulium/data/collate.py
thulium/data/datasets.py
thulium/data/language_profiles.py
thulium/data/loaders.py
thulium/data/noise_injection.py
thulium/data/samplers.py
thulium/data/transforms.py
thulium/evaluation/__init__.py
thulium/evaluation/benchmarking.py
thulium/evaluation/calibration.py
thulium/evaluation/metrics.py
thulium/evaluation/reporting.py
thulium/evaluation/robustness.py
thulium/models/__init__.py
thulium/models/backbones/cnn_backbones.py
thulium/models/backbones/vit_backbones.py
thulium/models/decoders/attention_decoder.py
thulium/models/decoders/ctc_decoder.py
thulium/models/language_models/__init__.py
thulium/models/language_models/char_lm.py
thulium/models/language_models/ngram_lm.py
thulium/models/language_models/word_lm.py
thulium/models/segmentation/__init__.py
thulium/models/segmentation/line_segmentation.py
thulium/models/segmentation/word_segmentation.py
thulium/models/sequence/lstm_heads.py
thulium/models/sequence/transformer_heads.py
thulium/models/wrappers/htr_model.py
thulium/pipeline/__init__.py
thulium/pipeline/config.py
thulium/pipeline/form_pipeline.py
thulium/pipeline/htr_pipeline.py
thulium/pipeline/multi_language_pipeline.py
thulium/pipeline/segmentation_pipeline.py
thulium/text/__init__.py
thulium/text/normalization.py
thulium/training/__init__.py
thulium/training/checkpointing.py
thulium/training/early_stopping.py
thulium/training/trainer.py
thulium/xai/__init__.py
thulium/xai/attention_maps.py
thulium/xai/confidence_analysis.py
thulium/xai/error_analysis.py
thulium_htr-1.2.1.dist-info/licenses/AUTHORS.md
thulium_htr-1.2.1.dist-info/licenses/LICENSE
thulium_htr-1.2.1.dist-info/METADATA
thulium_htr-1.2.1.dist-info/WHEEL
thulium_htr-1.2.1.dist-info/entry_points.txt
thulium_htr-1.2.1.dist-info/top_level.txt
thulium_htr-1.2.1.dist-info/RECORD
