Metadata-Version: 2.4
Name: thulium-htr
Version: 1.2.1
Summary: Thulium - State-of-the-Art Multilingual Handwriting Text Recognition for Python
Author-email: Thulium Contributors <opensource@thulium.ai>
License:                                  Apache License
Project-URL: Homepage, https://github.com/olaflaitinen/Thulium
Project-URL: Bug Tracker, https://github.com/olaflaitinen/Thulium/issues
Project-URL: Documentation, https://thulium.readthedocs.io
Keywords: handwriting,ocr,htr,text-recognition,multilingual,deep-learning,pytorch,ctc,transformer,computer-vision,document-analysis,historical-documents
Classifier: Development Status :: 5 - Production/Stable
Classifier: Intended Audience :: Developers
Classifier: Intended Audience :: Science/Research
Classifier: Intended Audience :: Education
Classifier: License :: OSI Approved :: Apache Software License
Classifier: Programming Language :: Python :: 3
Classifier: Programming Language :: Python :: 3.10
Classifier: Programming Language :: Python :: 3.11
Classifier: Programming Language :: Python :: 3.12
Classifier: Topic :: Scientific/Engineering :: Artificial Intelligence
Classifier: Topic :: Scientific/Engineering :: Image Recognition
Classifier: Topic :: Text Processing :: General
Classifier: Topic :: Text Processing :: Linguistic
Classifier: Operating System :: OS Independent
Classifier: Natural Language :: English
Classifier: Natural Language :: German
Classifier: Natural Language :: French
Classifier: Natural Language :: Russian
Classifier: Natural Language :: Arabic
Classifier: Natural Language :: Chinese (Simplified)
Classifier: Natural Language :: Japanese
Classifier: Natural Language :: Korean
Requires-Python: >=3.10
License-File: LICENSE
License-File: AUTHORS.md
Requires-Dist: torch>=2.0.0
Requires-Dist: torchvision>=0.15.0
Requires-Dist: numpy>=1.21.0
Requires-Dist: Pillow>=9.0.0
Requires-Dist: PyYAML>=6.0
Requires-Dist: pydantic>=2.0.0
Requires-Dist: tqdm>=4.60.0
Requires-Dist: typer>=0.9.0
Requires-Dist: rich>=13.0.0
Requires-Dist: opencv-python-headless>=4.0.0
Requires-Dist: scikit-learn>=1.0.0
Requires-Dist: structlog>=23.0.0
Requires-Dist: editdistance>=0.6.0
Provides-Extra: dev
Requires-Dist: pytest>=7.0.0; extra == "dev"
Requires-Dist: pytest-cov>=4.0.0; extra == "dev"
Requires-Dist: black>=23.0.0; extra == "dev"
Requires-Dist: ruff>=0.0.260; extra == "dev"
Requires-Dist: mypy>=1.0.0; extra == "dev"
Requires-Dist: pre-commit>=3.0.0; extra == "dev"
Requires-Dist: mkdocs-material>=9.0.0; extra == "dev"
Provides-Extra: gpu
Requires-Dist: torch>=2.0.0; extra == "gpu"
Dynamic: license-file
